Camunda/Camunda.py
Camunda/__init__.py
Camunda/test_Camunda.py
camunda_utils-1.1.1.dist-info/licenses/LICENSE
camunda_utils-1.1.1.dist-info/METADATA
camunda_utils-1.1.1.dist-info/WHEEL
camunda_utils-1.1.1.dist-info/top_level.txt
camunda_utils-1.1.1.dist-info/RECORD
